MANIFEST.in
README.md
setup.py
cgpio/__init__.py
cgpio/cgpio.py
cgpio.egg-info/PKG-INFO
cgpio.egg-info/SOURCES.txt
cgpio.egg-info/dependency_links.txt
cgpio.egg-info/top_level.txt