Metadata-Version: 1.0
Name: cgpio
Version: 0.5
Summary: a gpio class
Home-page: http://fpdz.taobao.com
Author: caoxp
Author-email: fpdz2010@qq.com
License: MIT License
Keywords: gpio,class
Platform: any
